pharma_globex/__init__.py
pharma_globex/main.py
pharma_globex/prompts.py
pharma_globex-2025.12.21100525.dist-info/METADATA
pharma_globex-2025.12.21100525.dist-info/WHEEL
pharma_globex-2025.12.21100525.dist-info/top_level.txt
pharma_globex-2025.12.21100525.dist-info/RECORD
