Metadata-Version: 2.4
Name: pharma-globex
Version: 2025.12.21100525
Summary: A new package designed to analyze input texts related to global pharmaceutical trends, such as India's role in manufacturing generics, and generate structured summaries or insights. It leverages struc
Author-email: pharma-globex <hi@eugene.plus>
License: MIT
Project-URL: Homepage, https://github.com/chigwell/pharma-globex
Requires-Python: >=3.9
Requires-Dist: langchain-llm7>=0.0.0
Requires-Dist: llmatch-messages>=0.0.0
Requires-Dist: langchain-core>=0.3.0
